LICENSE
MANIFEST.in
README.rst
setup.py
test_requirements.txt
TWLogger.egg-info/PKG-INFO
TWLogger.egg-info/SOURCES.txt
TWLogger.egg-info/dependency_links.txt
TWLogger.egg-info/entry_points.txt
TWLogger.egg-info/not-zip-safe
TWLogger.egg-info/requires.txt
TWLogger.egg-info/top_level.txt
twlogger/__init__.py
twlogger/client.py
twlogger/handler.py
twlogger/improved_json.py
twlogger/middleware.py
twlogger/utils.py