Metadata-Version: 1.1
Name: TWLogger
Version: 0.1.0
Summary: Client for TaskWorkshop exceptions
Home-page: https://github.com/TaskWorkshop/taskworkshop-logger-python
Author: TaskWorkshop
Author-email: contact@taskworkshop.com
License:                     GNU GENERAL PUBLIC LICENSE
